/*
 * Copyright (C) 2022 Callum Seabrook <callum.seabrook@prevarinite.com>
 *
 * This program is free software; you can redistribute it and/or modify it under
 * the terms of the GNU General Public License as published by the Free Software
 * Foundation; version 2.
 *
 * This program is distributed in the hope that it will be useful, but WITHOUT
 * ANY WARRANTY; without even the implied warranty of MERCHANTABILITY or FITNESS
 * FOR A PARTICULAR PURPOSE. See the GNU General Public License for more details.
 *
 * You should have received a copy of the GNU General Public License along with
 * this program; if not, write to the Free Software Foundation, Inc., 51 Franklin
 * Street, Fifth Floor, Boston, MA 02110-1301, USA.
 */

pub(super) const NOP: u8 = 0;
pub(super) const ACONST_NULL: u8 = 1;
pub(super) const ICONST_M1: u8 = 2;
pub(super) const ICONST_0: u8 = 3;
pub(super) const ICONST_5: u8 = 8;
pub(super) const LCONST_0: u8 = 9;
pub(super) const LCONST_1: u8 = 10;
pub(super) const FCONST_0: u8 = 11;
pub(super) const FCONST_2: u8 = 13;
pub(super) const DCONST_0: u8 = 14;
pub(super) const DCONST_1: u8 = 15;
pub(super) const BIPUSH: u8 = 16;
pub(super) const SIPUSH: u8 = 17;
//pub(super) const LDC: u8 = 18;
//pub(super) const LDC_W: u8 = 19;
//pub(super) const LDC2_W: u8 = 20;
pub(super) const ILOAD: u8 = 21;
pub(super) const LLOAD: u8 = 22;
pub(super) const FLOAD: u8 = 23;
pub(super) const DLOAD: u8 = 24;
pub(super) const ALOAD: u8 = 25;
pub(super) const ILOAD_0: u8 = 26;
pub(super) const ILOAD_3: u8 = 29;
pub(super) const LLOAD_0: u8 = 30;
pub(super) const LLOAD_3: u8 = 33;
pub(super) const FLOAD_0: u8 = 34;
pub(super) const FLOAD_3: u8 = 37;
pub(super) const DLOAD_0: u8 = 38;
pub(super) const DLOAD_3: u8 = 41;
pub(super) const ALOAD_0: u8 = 42;
pub(super) const ALOAD_3: u8 = 45;
pub(super) const IALOAD: u8 = 46;
pub(super) const LALOAD: u8 = 47;
pub(super) const FALOAD: u8 = 48;
pub(super) const DALOAD: u8 = 49;
pub(super) const AALOAD: u8 = 50;
pub(super) const BALOAD: u8 = 51;
pub(super) const CALOAD: u8 = 52;
pub(super) const SALOAD: u8 = 53;
pub(super) const ISTORE: u8 = 54;
pub(super) const LSTORE: u8 = 55;
pub(super) const FSTORE: u8 = 56;
pub(super) const DSTORE: u8 = 57;
pub(super) const ASTORE: u8 = 58;
pub(super) const ISTORE_0: u8 = 59;
pub(super) const ISTORE_3: u8 = 62;
pub(super) const LSTORE_0: u8 = 63;
pub(super) const LSTORE_3: u8 = 66;
pub(super) const FSTORE_0: u8 = 67;
pub(super) const FSTORE_3: u8 = 70;
pub(super) const DSTORE_0: u8 = 71;
pub(super) const DSTORE_3: u8 = 74;
pub(super) const ASTORE_0: u8 = 75;
pub(super) const ASTORE_3: u8 = 78;
pub(super) const IASTORE: u8 = 79;
pub(super) const LASTORE: u8 = 80;
pub(super) const FASTORE: u8 = 81;
pub(super) const DASTORE: u8 = 82;
pub(super) const AASTORE: u8 = 83;
pub(super) const BASTORE: u8 = 84;
pub(super) const CASTORE: u8 = 85;
pub(super) const SASTORE: u8 = 86;
pub(super) const POP: u8 = 87;
pub(super) const POP2: u8 = 88;
pub(super) const DUP: u8 = 89;
pub(super) const DUP_X1: u8 = 90;
pub(super) const DUP_X2: u8 = 91;
pub(super) const DUP2: u8 = 92;
pub(super) const DUP2_X1: u8 = 93;
pub(super) const DUP2_X2: u8 = 94;
pub(super) const SWAP: u8 = 95;
pub(super) const IADD: u8 = 96;
pub(super) const LADD: u8 = 97;
pub(super) const FADD: u8 = 98;
pub(super) const DADD: u8 = 99;
pub(super) const ISUB: u8 = 100;
pub(super) const LSUB: u8 = 101;
pub(super) const FSUB: u8 = 102;
pub(super) const DSUB: u8 = 103;
pub(super) const IMUL: u8 = 104;
pub(super) const LMUL: u8 = 105;
pub(super) const FMUL: u8 = 106;
pub(super) const DMUL: u8 = 107;
pub(super) const IDIV: u8 = 108;
pub(super) const LDIV: u8 = 109;
pub(super) const FDIV: u8 = 110;
pub(super) const DDIV: u8 = 111;
pub(super) const IREM: u8 = 112;
pub(super) const LREM: u8 = 113;
pub(super) const FREM: u8 = 114;
pub(super) const DREM: u8 = 115;
pub(super) const INEG: u8 = 116;
pub(super) const LNEG: u8 = 117;
pub(super) const FNEG: u8 = 118;
pub(super) const DNEG: u8 = 119;
pub(super) const ISHL: u8 = 120;
pub(super) const LSHL: u8 = 121;
pub(super) const ISHR: u8 = 122;
pub(super) const LSHR: u8 = 123;
pub(super) const IUSHR: u8 = 124;
pub(super) const LUSHR: u8 = 125;
pub(super) const IAND: u8 = 126;
pub(super) const LAND: u8 = 127;
pub(super) const IOR: u8 = 128;
pub(super) const LOR: u8 = 129;
pub(super) const IXOR: u8 = 130;
pub(super) const LXOR: u8 = 131;
pub(super) const IINC: u8 = 132;
pub(super) const I2L: u8 = 133;
pub(super) const I2F: u8 = 134;
pub(super) const I2D: u8 = 135;
pub(super) const L2I: u8 = 136;
pub(super) const L2F: u8 = 137;
pub(super) const L2D: u8 = 138;
pub(super) const F2I: u8 = 139;
pub(super) const F2L: u8 = 140;
pub(super) const F2D: u8 = 141;
pub(super) const D2I: u8 = 142;
pub(super) const D2L: u8 = 143;
pub(super) const D2F: u8 = 144;
pub(super) const I2B: u8 = 145;
pub(super) const I2C: u8 = 146;
pub(super) const I2S: u8 = 147;
pub(super) const LCMP: u8 = 148;
pub(super) const FCMPL: u8 = 149;
pub(super) const FCMPG: u8 = 150;
pub(super) const DCMPL: u8 = 151;
pub(super) const DCMPG: u8 = 152;
pub(super) const IFEQ: u8 = 153;
pub(super) const IFNE: u8 = 154;
pub(super) const IFLT: u8 = 155;
pub(super) const IFGE: u8 = 156;
pub(super) const IFGT: u8 = 157;
pub(super) const IFLE: u8 = 158;
pub(super) const IF_ICMPEQ: u8 = 159;
pub(super) const IF_ICMPNE: u8 = 160;
pub(super) const IF_ICMPLT: u8 = 161;
pub(super) const IF_ICMPGE: u8 = 162;
pub(super) const IF_ICMPGT: u8 = 163;
pub(super) const IF_ICMPLE: u8 = 164;
pub(super) const IF_ACMPEQ: u8 = 165;
pub(super) const IF_ACMPNE: u8 = 166;
pub(super) const GOTO: u8 = 167;
pub(super) const JSR: u8 = 168;
//pub(super) const RET: u8 = 169;
//pub(super) const TABLESWITCH: u8 = 170;
//pub(super) const LOOKUPSWITCH: u8 = 171;
pub(super) const IRETURN: u8 = 172;
pub(super) const LRETURN: u8 = 173;
pub(super) const FRETURN: u8 = 174;
pub(super) const DRETURN: u8 = 175;
pub(super) const ARETURN: u8 = 176;
pub(super) const RETURN: u8 = 177;
//pub(super) const GETSTATIC: u8 = 178;
//pub(super) const PUTSTATIC: u8 = 179;
//pub(super) const GETFIELD: u8 = 180;
//pub(super) const PUTFIELD: u8 = 181;
//pub(super) const INVOKEVIRTUAL: u8 = 182;
//pub(super) const INVOKESPECIAL: u8 = 183;
//pub(super) const INVOKESTATIC: u8 = 184;
//pub(super) const INVOKEINTERFACE: u8 = 185;
//pub(super) const INVOKEDYNAMIC: u8 = 186;
pub(super) const NEW: u8 = 187;
pub(super) const NEWARRAY: u8 = 188;
pub(super) const ANEWARRAY: u8 = 189;
pub(super) const ARRAYLENGTH: u8 = 190;
pub(super) const ATHROW: u8 = 191;
pub(super) const CHECKCAST: u8 = 192;
pub(super) const INSTANCEOF: u8 = 193;
//pub(super) const MONITORENTER: u8 = 194;
//pub(super) const MONITOREXIT: u8 = 195;
//pub(super) const WIDE: u8 = 196;
//pub(super) const MULTIANEWARRAY: u8 = 197;
pub(super) const IFNULL: u8 = 198;
pub(super) const IFNONNULL: u8 = 199;
pub(super) const GOTO_W: u8 = 200;
pub(super) const JSR_W: u8 = 201;
//pub(super) const BREAKPOINT: u8 = 202; // Debug only
